web3_multicall/__init__.py
web3_multicall/_abi.py
web3_multicall/multicall.py
web3_multicall/_utils/__init__.py
web3_multicall/_utils/_function_signature.py
web3_multicall/_utils/function.py
web3_multicall/models/__init__.py
web3_multicall/models/aggregate_result.py
web3_multicall/models/function_input.py
web3_multicall/models/function_result.py
web3_multicall/models/enums/__init__.py
web3_multicall/models/enums/network.py
web3_multicall-0.0.7.dist-info/LICENSE
web3_multicall-0.0.7.dist-info/METADATA
web3_multicall-0.0.7.dist-info/WHEEL
web3_multicall-0.0.7.dist-info/top_level.txt
web3_multicall-0.0.7.dist-info/RECORD
