Metadata-Version: 2.1
Name: web3-multicall
Version: 0.0.7
Summary: web3_multicall
Home-page: https://github.com/kkristof200/py_web3_multicall
Author: Kristóf-Attila Kovács
License: UNKNOWN
Platform: UNKNOWN
Classifier: Programming Language :: Python :: 3.4
Classifier: Programming Language :: Python :: 3.5
Classifier: Programming Language :: Python :: 3.6
Classifier: Programming Language :: Python :: 3.7
Classifier: Programming Language :: Python :: 3.8
Classifier: Programming Language :: Python :: 3.9
Classifier: License :: OSI Approved :: MIT License
Classifier: Operating System :: OS Independent
Requires-Python: >=3.4
License-File: LICENSE
Requires-Dist: eth-abi (>=2.1.1)
Requires-Dist: eth-utils (>=1.10.0)
Requires-Dist: jsoncodable (>=0.1.7)
Requires-Dist: kw3 (>=0.0.16)
Requires-Dist: web3 (>=5.23.1)
Requires-Dist: web3-wrapped-contract (>=0.0.15)
